setup.py
piriti/__init__.py
piriti/app.py
piriti/config.py
piriti/configure.py
piriti/data_pack.py
piriti/exceptions.py
piriti/formats.py
piriti/listener.py
piriti/message_distributor.py
piriti/path.py
piriti/storage.py
piriti.egg-info/PKG-INFO
piriti.egg-info/SOURCES.txt
piriti.egg-info/dependency_links.txt
piriti.egg-info/requires.txt
piriti.egg-info/top_level.txt
test/test_distributor.py
test/test_path.py
test/test_storage.py