Metadata-Version: 1.0
Name: piriti
Version: 1.0.0.dev2
Summary: Bridge between HTTP POST messages and WebSockets
Home-page: https://github.com/voidpp/piriti
Author: Lajos Santa
Author-email: santa.lajos@coldline.hu
License: UNKNOWN
Platform: UNKNOWN
